{
	"name": "ds_raw_dw_ecdc",
	"properties": {
		"linkedServiceName": {
			"referenceName": "ls_project_dw",
			"type": "LinkedServiceReference"
		},
		"parameters": {
			"sinkFileName": {
				"type": "string"
			}
		},
		"folder": {
			"name": "raw"
		},
		"annotations": [],
		"type": "DelimitedText",
		"typeProperties": {
			"location": {
				"type": "AzureBlobFSLocation",
				"fileName": {
					"value": "@dataset().sinkFileName",
					"type": "Expression"
				},
				"folderPath": {
					"value": "@replace(dataset().sinkFileName, '.csv','')",
					"type": "Expression"
				},
				"fileSystem": "raw"
			},
			"columnDelimiter": ",",
			"escapeChar": "\\",
			"firstRowAsHeader": true,
			"quoteChar": "\""
		},
		"schema": []
	}
}